setup.py
txzookeeper/__init__.py
txzookeeper/client.py
txzookeeper/lock.py
txzookeeper/managed.py
txzookeeper/node.py
txzookeeper/queue.py
txzookeeper/retry.py
txzookeeper/utils.py
txzookeeper.egg-info/PKG-INFO
txzookeeper.egg-info/SOURCES.txt
txzookeeper.egg-info/dependency_links.txt
txzookeeper.egg-info/top_level.txt
txzookeeper/tests/__init__.py
txzookeeper/tests/common.py
txzookeeper/tests/mocker.py
txzookeeper/tests/proxy.py
txzookeeper/tests/test_client.py
txzookeeper/tests/test_conn_failure.py
txzookeeper/tests/test_lock.py
txzookeeper/tests/test_managed.py
txzookeeper/tests/test_node.py
txzookeeper/tests/test_queue.py
txzookeeper/tests/test_retry.py
txzookeeper/tests/test_security.py
txzookeeper/tests/test_session.py
txzookeeper/tests/test_utils.py
txzookeeper/tests/utils.py