Metadata-Version: 1.1
Name: txzookeeper
Version: 0.9.8
Summary: Twisted api for Apache Zookeeper
Home-page: https://launchpad.net/txzookeeper
Author: Juju Developers
Author-email: juju@lists.ubuntu.com
License: LGPL
Platform: UNKNOWN
Classifier: Intended Audience :: Developers
Classifier: Intended Audience :: System Administrators
Classifier: Intended Audience :: Information Technology
Classifier: Programming Language :: Python
Classifier: Topic :: Database
Classifier: License :: OSI Approved :: GNU Library or Lesser General Public License (LGPL)
